a.py
testLidamao-0.11.dist-info/METADATA
testLidamao-0.11.dist-info/WHEEL
testLidamao-0.11.dist-info/top_level.txt
testLidamao-0.11.dist-info/RECORD
