Metadata-Version: 2.1
Name: testLidamao
Version: 0.11
Summary: A simple flask utils toolkit
Home-page: UNKNOWN
Author: lidamao
Author-email: lee-perfect@qq.com
License: UNKNOWN
Platform: UNKNOWN
Requires-Dist: Flask (==1.0.2)
